leia/__init__.py
leia/leia.py
leia-0.1.0.dist-info/AUTHORS.md
leia-0.1.0.dist-info/LICENSE
leia-0.1.0.dist-info/METADATA
leia-0.1.0.dist-info/WHEEL
leia-0.1.0.dist-info/top_level.txt
leia-0.1.0.dist-info/RECORD
